cordic/cordic.vhd
----------------------------------------------------------------------------------
-- Company: Personal
-- Engineer: Jose Segura Montes
-- 
-- Create Date: 2026
-- Design Name: FPGA-Accelerated N-DOF Industrial Robot Kinematics
-- Module Name: cordic - rtl
-- Project Name: ros2-fpga
-- Target Devices: Generic FPGA (Xilinx/Intel)
-- Tool Versions: GHDL / Vivado / Quartus
-- Description: High-performance, parameterizable VHDL-based Direct Kinematics 
--              solver for a N-DOF industrial robot. Implements a 
--              pipelined architecture using Parallel CORDICs (trigonometric 
--              functions) and a custom Matrix Multiplier (4x4) operating under 
--              a robust Qx.y fixed-point arithmetic system.
--
-- Dependencies: robot_config_pkg
-- 
-- Revision: 13/09/2026
--
-- Copyright (c) 2026 Jose Segura Montes. All rights reserved.
-- This code is licensed under proprietary/open-source terms as applicable.
----------------------------------------------------------------------------------

----------------------------------------------------------------------------------
-- Architecture & Interface Documentation
-- 
-- Entity Name: cordic
-- Purpose: Implements a pipelined CORDIC algorithm for computing trigonometric functions.
--
-- Inputs:
--   * clk      (std_logic)              : System clock driving the internal FSM pipeline.
--   * reset    (std_logic)              : Asynchronous active-high reset signal.
--   * start    (std_logic)              : Single-cycle trigger pulse to initiate computation.
--   * angle_in (fp_type)                : Input angle in fixed-point representation (Qx.y format).
-- 
--
-- Outputs:
--   * sin_out  (fp_type)                : Sine of the input angle.
--   * cos_out  (fp_type)                : Cosine of the input angle.
--   * done     (std_logic)              : Completion flag asserted for one clock cycle.
----------------------------------------------------------------------------------

library ieee;
use ieee.std_logic_1164.all;
use ieee.numeric_std.all;
use ieee.math_real.all;
use work.robot_config_pkg.all;

entity cordic is
    generic (
        ITERATIONS : integer := 24;
        DATA_WIDTH : integer := 32
    );
    port (
        clk      : in  std_logic;
        reset    : in  std_logic;
        start    : in  std_logic;
        angle_in : in  fp_type;
        sin_out  : out fp_type;
        cos_out  : out fp_type;
        done     : out std_logic
    );
end entity cordic;

architecture rtl of cordic is
    
    -- FSM Types
    type state_type is (IDLE, CALCULATING, FINISHED);
    signal state : state_type := IDLE;
    
    signal x_reg, y_reg, z_reg : fp_type;
    signal iter_counter        : integer range 0 to ITERATIONS;

    -- Scale factor for fixed-point conversion (2^FRAC_WIDTH)
    constant SCALE_FACTOR : real := 2.0 ** real(FRAC_WIDTH);

    -- Constant K (0.607252935)
    constant K_GAIN : fp_type := to_signed(integer(0.607252935 * SCALE_FACTOR), TOTAL_WIDTH);

    -- atan LUT for CORDIC iterations
    type atan_array_type is array (0 to ITERATIONS-1) of fp_type;
    function init_atan_table return atan_array_type is
        variable table : atan_array_type;
    begin
        for i in 0 to ITERATIONS-1 loop
            -- Utiliza arctan de la librería math_real y escala al punto fijo actual
            table(i) := to_signed(integer(arctan(1.0 / (2.0 ** real(i))) * SCALE_FACTOR), TOTAL_WIDTH);
        end loop;
        return table;
    end function;
    constant ATAN_TABLE : atan_array_type := init_atan_table;

begin
    process(clk, reset)
    begin
        if reset = '1' then
            state <= IDLE;
            done <= '0';
            sin_out <= (others => '0');
            cos_out <= (others => '0');
            x_reg <= (others => '0');
            y_reg <= (others => '0');
            z_reg <= (others => '0');
            iter_counter <= 0;

        elsif rising_edge(clk) then   
            case state is
                when IDLE =>
                    if start = '1' then
                        x_reg <= K_GAIN; 
                        y_reg <= (others => '0');
                        z_reg <= angle_in;
                        iter_counter <= 0;
                        state <= CALCULATING;
                        done <= '0';
                    end if;

                -- Algorithmic CORDIC rotation mode implementation
                when CALCULATING =>
                    if iter_counter = ITERATIONS then
                        state <= FINISHED;
                    else
                        if z_reg(TOTAL_WIDTH-1) = '0' then
                            x_reg <= x_reg - shift_right(y_reg, iter_counter);
                            y_reg <= y_reg + shift_right(x_reg, iter_counter);
                            z_reg <= z_reg - ATAN_TABLE(iter_counter);
                        else
                            x_reg <= x_reg + shift_right(y_reg, iter_counter);
                            y_reg <= y_reg - shift_right(x_reg, iter_counter);
                            z_reg <= z_reg + ATAN_TABLE(iter_counter);
                        end if;
                        
                        iter_counter <= iter_counter + 1;
                    end if;

                when FINISHED =>
                    sin_out <= y_reg;
                    cos_out <= x_reg;
                    done <= '1';
                    state <= IDLE;
            end case;
        end if;
    end process;
end architecture rtl;

common/cordic/cordic_tb.vhd
library ieee;
use ieee.std_logic_1164.all;
use ieee.numeric_std.all;

entity cordic_tb is
end entity cordic_tb;

architecture sim of cordic_tb is

    constant DATA_WIDTH : integer := 16;
    constant ITERATIONS : integer := 15;
    
    signal clk      : std_logic := '0';
    signal reset    : std_logic := '0';
    signal start    : std_logic := '0';
    signal angle_in : signed(DATA_WIDTH-1 downto 0) := (others => '0');
    
    signal sin_out  : signed(DATA_WIDTH-1 downto 0);
    signal cos_out  : signed(DATA_WIDTH-1 downto 0);
    signal done     : std_logic;

begin

    -- (UUT - Unit Under Test)
    UUT: entity work.cordic
        generic map (
            DATA_WIDTH => DATA_WIDTH,
            ITERATIONS => ITERATIONS
        )
        port map (
            clk      => clk,
            reset    => reset,
            start    => start,
            angle_in => angle_in,
            sin_out  => sin_out,
            cos_out  => cos_out,
            done     => done
        );

    -- (100 MHz)
    clk_process: process
    begin
        clk <= '0';
        wait for 5 ns;
        clk <= '1';
        wait for 5 ns;
    end process;

    stim_process: process
    begin
        -- Initial reset
        reset <= '1';
        wait for 20 ns;
        reset <= '0';
        wait for 20 ns;
        
        -- 45º (pi/4 = 0.785398 rad)
        -- Scale Q2.14: 0.785398 * 2^14 = 12868
        angle_in <= to_signed(12868, DATA_WIDTH);
        start <= '1';
        wait for 10 ns;
        start <= '0';
        wait until done = '1';
        wait for 50 ns;
        
        -- 30º (pi/6 = 0.523598 rad)
        -- Scale Q2.14: 0.523598 * 2^14 = 8578
        angle_in <= to_signed(8578, DATA_WIDTH);
        start <= '1';
        wait for 10 ns;
        start <= '0';
        wait until done = '1';
        wait for 50 ns;
        
        wait; 
    end process;

end architecture sim;

-- ghdl -a cordic.vhd               
-- ghdl -a cordic_tb.vhd            
-- ghdl -e cordic_tb                
-- ghdl -r cordic_tb --vcd=ondas.vcd --stop-time=1000ns

cordic/ondas.vcd
$date
  Sun Sep 13 11:03:11 2026
$end
$version
  GHDL v0
$end
$timescale
  1 fs
$end
$scope module standard $end
$upscope $end
$scope module std_logic_1164 $end
$upscope $end
$scope module numeric_std $end
$upscope $end
$scope module math_real $end
$upscope $end
$scope module cordic_tb $end
$var reg 1 ! clk $end
$var reg 1 " reset $end
$var reg 1 # start $end
$var reg 16 $ angle_in[15:0] $end
$var reg 16 % sin_out[15:0] $end
$var reg 16 & cos_out[15:0] $end
$var reg 1 ' done $end
$scope module uut $end
$var reg 1 ( clk $end
$var reg 1 ) reset $end
$var reg 1 * start $end
$var reg 16 + angle_in[15:0] $end
$var reg 16 , sin_out[15:0] $end
$var reg 16 - cos_out[15:0] $end
$var reg 1 . done $end
$comment state is not handled $end
$var reg 16 / x_reg[15:0] $end
$var reg 16 0 y_reg[15:0] $end
$var reg 16 1 z_reg[15:0] $end
$var integer 32 2 iter_counter $end
$upscope $end
$upscope $end
$enddefinitions $end
#0
0!
1"
0#
b0000000000000000 $
b0000000000000000 %
b0000000000000000 &
0'
0(
1)
0*
b0000000000000000 +
b0000000000000000 ,
b0000000000000000 -
0.
b0000000000000000 /
b0000000000000000 0
b0000000000000000 1
b0 2
#5000000
1!
1(
#10000000
0!
0(
#15000000
1!
1(
#20000000
0!
0"
0(
0)
#25000000
1!
1(
#30000000
0!
0(
#35000000
1!
1(
#40000000
0!
1#
b0011001001000100 $
0(
1*
b0011001001000100 +
#45000000
1!
1(
b0010011011011101 /
b0011001001000100 1
#50000000
0!
0#
0(
0*
#55000000
1!
1(
b0010011011011101 0
b0000000000000000 1
b1 2
#60000000
0!
0(
#65000000
1!
1(
b0001001101101111 /
b0011101001001011 0
b1110001001010100 1
b10 2
#70000000
0!
0(
#75000000
1!
1(
b0010001000000001 /
b0011010101110000 0
b1111001000000010 1
b11 2
#80000000
0!
0(
#85000000
1!
1(
b0010100010101111 /
b0011000100110000 0
b1111100111110111 1
b100 2
#90000000
0!
0(
#95000000
1!
1(
b0010101111000010 /
b0010111010100110 0
b1111110111110110 1
b101 2
#100000000
0!
0(
#105000000
1!
1(
b0010110100110111 /
b0010110101001000 0
b1111111111110110 1
b110 2
#110000000
0!
0(
#115000000
1!
1(
b0010110111101100 /
b0010110010010100 0
b0000000011110110 1
b111 2
#120000000
0!
0(
#125000000
1!
1(
b0010110110010011 /
b0010110011101111 0
b0000000001110110 1
b1000 2
#130000000
0!
0(
#135000000
1!
1(
b0010110101100111 /
b0010110100011100 0
b0000000000110110 1
b1001 2
#140000000
0!
0(
#145000000
1!
1(
b0010110101010001 /
b0010110100110010 0
b0000000000010110 1
b1010 2
#150000000
0!
0(
#155000000
1!
1(
b0010110101000110 /
b0010110100111101 0
b0000000000000110 1
b1011 2
#160000000
0!
0(
#165000000
1!
1(
b0010110101000001 /
b0010110101000010 0
b1111111111111110 1
b1100 2
#170000000
0!
0(
#175000000
1!
1(
b0010110101000011 /
b0010110101000000 0
b0000000000000010 1
b1101 2
#180000000
0!
0(
#185000000
1!
1(
b0010110101000010 /
b0010110101000001 0
b0000000000000000 1
b1110 2
#190000000
0!
0(
#195000000
1!
1(
b1111111111111111 1
b1111 2
#200000000
0!
0(
#205000000
1!
1(
#210000000
0!
0(
#215000000
1!
b0010110101000001 %
b0010110101000010 &
1'
1(
b0010110101000001 ,
b0010110101000010 -
1.
#220000000
0!
0(
#225000000
1!
1(
#230000000
0!
0(
#235000000
1!
1(
#240000000
0!
0(
#245000000
1!
1(
#250000000
0!
0(
#255000000
1!
1(
#260000000
0!
0(
#265000000
1!
1#
b0010000110000010 $
0'
1(
1*
b0010000110000010 +
0.
b0010011011011101 /
b0000000000000000 0
b0010000110000010 1
b0 2
#270000000
0!
0(
#275000000
1!
0#
1(
0*
b0010011011011101 0
b1110111100111110 1
b1 2
#280000000
0!
0(
#285000000
1!
1(
b0011101001001011 /
b0001001101101111 0
b0000110011101010 1
b10 2
#290000000
0!
0(
#295000000
1!
1(
b0011010101110000 /
b0010001000000001 0
b1111110100111100 1
b11 2
#300000000
0!
0(
#305000000
1!
1(
b0011100110110000 /
b0001101101010011 0
b0000010100110001 1
b100 2
#310000000
0!
0(
#315000000
1!
1(
b0011011111111011 /
b0001111011101110 0
b0000000100110010 1
b101 2
#320000000
0!
0(
#325000000
1!
1(
b0011011100000100 /
b0010000010101101 0
b1111111100110010 1
b110 2
#330000000
0!
0(
#335000000
1!
1(
b0011011110000110 /
b0001111111010001 0
b0000000000110010 1
b111 2
#340000000
0!
0(
#345000000
1!
1(
b0011011101000111 /
b0010000001000000 0
b1111111110110010 1
b1000 2
#350000000
0!
0(
#355000000
1!
1(
b0011011101100111 /
b0010000000001001 0
b1111111111110010 1
b1001 2
#360000000
0!
0(
#365000000
1!
1(
b0011011101110111 /
b0001111111101110 0
b0000000000010010 1
b1010 2
#370000000
0!
0(
#375000000
1!
1(
b0011011101110000 /
b0001111111111011 0
b0000000000000010 1
b1011 2
#380000000
0!
0(
#385000000
1!
1(
b0011011101101101 /
b0010000000000001 0
b1111111111111010 1
b1100 2
#390000000
0!
0(
#395000000
1!
1(
b0011011101101111 /
b0001111111111110 0
b1111111111111110 1
b1101 2
#400000000
0!
0(
#405000000
1!
1(
b0001111111111101 0
b0000000000000000 1
b1110 2
#410000000
0!
0(
#415000000
1!
1(
b1111111111111111 1
b1111 2
#420000000
0!
0(
#425000000
1!
1(
#430000000
0!
0(
#435000000
1!
b0001111111111101 %
b0011011101101111 &
1'
1(
b0001111111111101 ,
b0011011101101111 -
1.
